Metadata-Version: 2.1
Name: pyvrs
Version: 0.1
Summary: A powerful voice recognition library made in python. This combines several libraries in order to achieve a 'Voice Assistant' ready library.
Home-page: https://github.com/bossauh/pyvrs
Author: Philippe Mathew
Author-email: philmattdev@gmail.com
License: MIT
Download-URL: https://github.com/bossauh/pyvrs/archive/refs/tags/v_01.tar.gz
Keywords: voice,speech to text,voice recognition
Platform: UNKNOWN
License-File: LICENSE
